cdt_identity/__init__.py
cdt_identity/admin.py
cdt_identity/apps.py
cdt_identity/claims.py
cdt_identity/client.py
cdt_identity/hooks.py
cdt_identity/models.py
cdt_identity/routes.py
cdt_identity/session.py
cdt_identity/urls.py
cdt_identity/views.py
cdt_identity/migrations/0001_initial.py
cdt_identity/migrations/__init__.py
django_cdt_identity-2025.10.3.dist-info/licenses/LICENSE
django_cdt_identity-2025.10.3.dist-info/METADATA
django_cdt_identity-2025.10.3.dist-info/WHEEL
django_cdt_identity-2025.10.3.dist-info/top_level.txt
django_cdt_identity-2025.10.3.dist-info/RECORD
