Metadata-Version: 2.4
Name: django-cdt-identity
Version: 2025.10.3
Summary: Django client for identity proofing and claims verification with the California Department of Technology's Identity Gateway.
Maintainer-email: Compiler LLC <dev@compiler.la>
License:                     GNU AFFERO GENERAL PUBLIC LICENSE
Project-URL: Code, https://github.com/compilerla/django-cdt-identity
Project-URL: Issues, https://github.com/compilerla/django-cdt-identity/issues
Classifier: Programming Language :: Python :: 3 :: Only
Requires-Python: >=3.11
License-File: LICENSE
Requires-Dist: Authlib>=1.6.5
Requires-Dist: Django>=5.2.7
Requires-Dist: requests>=2.32.5
Provides-Extra: dev
Requires-Dist: black; extra == "dev"
Requires-Dist: djlint; extra == "dev"
Requires-Dist: flake8; extra == "dev"
Requires-Dist: pre-commit; extra == "dev"
Requires-Dist: setuptools_scm>=8; extra == "dev"
Provides-Extra: test
Requires-Dist: coverage; extra == "test"
Requires-Dist: pytest; extra == "test"
Requires-Dist: pytest-django; extra == "test"
Requires-Dist: pytest-mock; extra == "test"
Requires-Dist: pytest-socket; extra == "test"
Dynamic: license-file
